src/__init__.py
src/server.py
mseep_jobspy_mcp_server-0.1.3.dist-info/METADATA
mseep_jobspy_mcp_server-0.1.3.dist-info/WHEEL
mseep_jobspy_mcp_server-0.1.3.dist-info/RECORD
